unrobot/__init__.py
unrobot/joints.py
unrobot/kinematics.py
unrobot/model.py
unrobot/robot.py
unrobot-1.0.2.dist-info/METADATA
unrobot-1.0.2.dist-info/WHEEL
unrobot-1.0.2.dist-info/top_level.txt
unrobot-1.0.2.dist-info/RECORD
