Metadata-Version: 2.4
Name: unrobot
Version: 1.0.2
Summary: unrobot is a simple robot descriptor loader and toolkit for robotics applications.
Home-page: https://github.com/Churros98/unrobot
Author: Sofiane
Author-email: Churros98@example.com
License: MIT
Classifier: Development Status :: 1 - Planning
Classifier: Intended Audience :: Science/Research
Classifier: License :: OSI Approved :: MIT License
Classifier: Operating System :: POSIX :: Linux
Classifier: Programming Language :: Python :: 2
Classifier: Programming Language :: Python :: 2.7
Classifier: Programming Language :: Python :: 3
Classifier: Programming Language :: Python :: 3.4
Classifier: Programming Language :: Python :: 3.5
Requires-Python: >=2.7
Requires-Dist: pydantic==2.12.4
Dynamic: author
Dynamic: author-email
Dynamic: classifier
Dynamic: home-page
Dynamic: license
Dynamic: requires-dist
Dynamic: requires-python
Dynamic: summary
